{"nightTab":true,"version":"7.3.0","state":{"layout":{"area":{"header":{"width":100,"justify":"center"},"bookmark":{"width":100,"justify":"center"}},"alignment":"center-center","order":"header-bookmark","direction":"vertical","size":100,"width":80,"padding":40,"gutter":20,"breakpoint":"xxl","scrollbar":"auto","title":"","favicon":"","overscroll":false},"header":{"item":{"justify":"center"},"greeting":{"show":false,"type":"good","custom":"","name":"","size":100,"newLine":false},"transitional":{"show":false,"type":"time-and-date","size":100,"newLine":false},"clock":{"hour":{"show":true,"display":"number"},"minute":{"show":true,"display":"number"},"second":{"show":false,"display":"number"},"separator":{"show":true,"text":""},"meridiem":{"show":false},"hour24":{"show":true},"size":100,"newLine":false},"date":{"day":{"show":false,"display":"word","weekStart":"monday","length":"long"},"date":{"show":true,"display":"number","ordinal":true},"month":{"show":true,"display":"word","length":"short","ordinal":true},"year":{"show":false,"display":"number"},"separator":{"show":true,"text":""},"format":"date-month","size":100,"newLine":false},"search":{"show":true,"width":{"by":"auto","size":30},"engine":{"selected":"custom","custom":{"name":"Yandex","url":"https://yandex.ru/search/?text=","queryName":"text"}},"text":{"justify":"center"},"size":100,"newLine":false,"newTab":false,"string":"тест клавиатуры"},"order":["clock","date","search","toolbar"],"edit":false},"bookmark":{"size":100,"url":{"show":true},"line":{"show":true},"shadow":{"show":true},"hoverScale":{"show":true},"orientation":"bottom","style":"block","newTab":false,"edit":false,"add":false,"show":true,"item":{}},"group":{"area":{"justify":"left"},"order":"header-body","name":{"size":100},"toolbar":{"size":100},"edit":false,"add":false},"toolbar":{"location":"header","position":"bottom-right","size":100,"accent":{"show":true},"add":{"show":true},"edit":{"show":true},"newLine":false},"theme":{"color":{"range":{"primary":{"h":264,"s":22}},"contrast":{"start":0,"end":100},"shades":14},"accent":{"hsl":{"h":0,"s":0,"l":55},"rgb":{"r":140,"g":140,"b":140},"random":{"active":false,"style":"any"},"cycle":{"active":false,"speed":300,"step":10}},"font":{"display":{"name":"Rubik","weight":400,"style":"normal"},"ui":{"name":"Inter","weight":400,"style":"normal"}},"background":{"type":"image","color":{"hsl":{"h":221,"s":47,"l":17},"rgb":{"r":23,"g":36,"b":64}},"gradient":{"angle":160,"start":{"hsl":{"h":206,"s":16,"l":40},"rgb":{"r":86,"g":104,"b":118}},"end":{"hsl":{"h":219,"s":28,"l":12},"rgb":{"r":22,"g":28,"b":39}}},"image":{"url":"https://i.imgur.com/Oa1rARe.jpg","blur":0,"grayscale":0,"scale":100,"accent":0,"opacity":100,"vignette":{"opacity":0,"start":90,"end":70}},"video":{"url":"","blur":0,"grayscale":0,"scale":100,"accent":0,"opacity":100,"vignette":{"opacity":0,"start":90,"end":70}}},"opacity":{"general":100},"layout":{"color":{"by":"theme","blur":0,"opacity":10,"hsl":{"h":0,"s":0,"l":0},"rgb":{"r":0,"g":0,"b":0}},"divider":{"size":0}},"header":{"color":{"by":"theme","opacity":10,"hsl":{"h":0,"s":0,"l":0},"rgb":{"r":0,"g":0,"b":0}},"search":{"opacity":100}},"bookmark":{"color":{"by":"theme","opacity":10,"hsl":{"h":0,"s":0,"l":0},"rgb":{"r":0,"g":0,"b":0}},"item":{"border":0,"opacity":100}},"group":{"toolbar":{"opacity":100}},"toolbar":{"opacity":100},"style":"dark","radius":75,"shadow":100,"shade":{"opacity":10,"blur":0},"custom":{"all":[],"edit":false}},"search":false,"modal":false,"menu":true},"bookmark":[{"name":{"text":"","show":true},"collapse":false,"toolbar":{"size":100,"openAll":{"show":true},"collapse":{"show":true}},"items":[{"url":"https://translate.yandex.ru/","display":{"alignment":"center-center","direction":"vertical","order":"visual-name","rotate":0,"translate":{"x":0,"y":0},"gutter":25,"name":{"show":false,"text":"Я.Переводчик","size":11},"visual":{"show":true,"type":"image","size":54,"letter":{"text":"Переводчик"},"icon":{"name":"","prefix":"","label":""},"image":{"url":"https://translate.yandex.ru/icons/favicon.ico"},"shadow":{"size":0}}},"accent":{"by":"custom","hsl":{"h":10,"s":97,"l":58},"rgb":{"r":252,"g":77,"b":44}},"color":{"by":"theme","hsl":{"h":10,"s":98,"l":59},"rgb":{"r":253,"g":84,"b":50},"opacity":100},"background":{"show":false,"type":"image","opacity":100,"image":{"url":""},"video":{"url":""}},"border":0,"shape":{"wide":false,"tall":false},"timestamp":1681064377259},{"url":"https://www.youtube.com/","display":{"alignment":"center-center","direction":"vertical","order":"visual-name","rotate":0,"translate":{"x":0,"y":0},"gutter":0,"name":{"show":false,"text":"YouTube","size":11},"visual":{"show":true,"type":"icon","size":58,"letter":{"text":"Youtube"},"icon":{"name":"youtube","prefix":"fab","label":"YouTube"},"image":{"url":""},"shadow":{"size":0}}},"accent":{"by":"custom","hsl":{"h":0,"s":100,"l":50},"rgb":{"r":255,"g":0,"b":0}},"color":{"by":"theme","hsl":{"h":0,"s":100,"l":50},"rgb":{"r":255,"g":0,"b":0},"opacity":100},"background":{"show":false,"type":"image","opacity":100,"image":{"url":""},"video":{"url":""}},"border":0,"shape":{"wide":false,"tall":false},"timestamp":1681064227294},{"url":"https://vk.com/im","display":{"alignment":"center-center","direction":"vertical","order":"visual-name","rotate":0,"translate":{"x":0,"y":0},"gutter":25,"name":{"show":false,"text":"VK","size":11},"visual":{"show":true,"type":"image","size":51,"letter":{"text":"VK"},"icon":{"name":"vk","prefix":"fab","label":"VK"},"image":{"url":"https://upload.wikimedia.org/wikipedia/commons/f/f3/VK_Compact_Logo_%282021-present%29.svg"},"shadow":{"size":0}}},"accent":{"by":"custom","hsl":{"h":212,"s":100,"l":50},"rgb":{"r":0,"g":119,"b":255}},"color":{"by":"theme","hsl":{"h":0,"s":0,"l":1},"rgb":{"r":3,"g":3,"b":3},"opacity":100},"background":{"show":false,"type":"image","opacity":100,"image":{"url":""},"video":{"url":""}},"border":0,"shape":{"wide":false,"tall":false},"timestamp":1681064248074},{"url":"https://v2.vost.pw/","display":{"alignment":"center-center","direction":"vertical","order":"visual-name","rotate":0,"translate":{"x":0,"y":0},"gutter":0,"name":{"show":false,"text":"AnimeVost","size":15},"visual":{"show":true,"type":"image","size":53,"letter":{"text":"AnimeVost"},"icon":{"name":"","prefix":"","label":""},"image":{"url":"https://v2.vost.pw/android-chrome-512x512.png"},"shadow":{"size":0}}},"accent":{"by":"custom","hsl":{"h":33,"s":82,"l":68},"rgb":{"r":240,"g":179,"b":105}},"color":{"by":"theme","hsl":{"h":0,"s":0,"l":0},"rgb":{"r":0,"g":0,"b":0},"opacity":100},"background":{"show":false,"type":"image","opacity":100,"image":{"url":""},"video":{"url":""}},"border":0,"shape":{"wide":false,"tall":false},"timestamp":1681064268984},{"url":"https://v3.astar.bz/","display":{"alignment":"center-center","direction":"vertical","order":"visual-name","rotate":0,"translate":{"x":0,"y":0},"gutter":25,"name":{"show":false,"text":"AniStar","size":15},"visual":{"show":true,"type":"image","size":45,"letter":{"text":"AniStar"},"icon":{"name":"","prefix":"","label":"https://v3.astar.bz/favicon2.png?r=1"},"image":{"url":"https://v3.astar.bz/favicon2.png?r=1"},"shadow":{"size":0}}},"accent":{"by":"custom","hsl":{"h":276,"s":69,"l":50},"rgb":{"r":146,"g":39,"b":216}},"color":{"by":"theme","hsl":{"h":278,"s":74,"l":23},"rgb":{"r":70,"g":15,"b":102},"opacity":100},"background":{"show":false,"type":"image","opacity":100,"image":{"url":""},"video":{"url":""}},"border":0,"shape":{"wide":false,"tall":false},"timestamp":1681064325634},{"url":"https://darklibria.it/releases/","display":{"alignment":"center-center","direction":"vertical","order":"visual-name","rotate":0,"translate":{"x":0,"y":0},"gutter":25,"name":{"show":false,"text":"DarkLibria","size":11},"visual":{"show":true,"type":"image","size":59,"letter":{"text":"DarkLibria"},"icon":{"name":"","prefix":"","label":""},"image":{"url":"https://darklibria.it/static/img/404.webp"},"shadow":{"size":0}}},"accent":{"by":"custom","hsl":{"h":358,"s":67,"l":51},"rgb":{"r":214,"g":47,"b":53}},"color":{"by":"theme","hsl":{"h":0,"s":0,"l":0},"rgb":{"r":0,"g":0,"b":0},"opacity":100},"background":{"show":false,"type":"image","opacity":100,"image":{"url":""},"video":{"url":""}},"border":0,"shape":{"wide":false,"tall":false},"timestamp":1681064353366},{"url":"https://vkplay.live/grpzdc","display":{"alignment":"center-center","direction":"vertical","order":"visual-name","rotate":0,"translate":{"x":0,"y":0},"gutter":25,"name":{"show":false,"text":"VkPlay.Live","size":7},"visual":{"show":true,"type":"image","size":100,"letter":{"text":""},"icon":{"name":"","prefix":"","label":""},"image":{"url":"https://static.vkplay.live/assets/images/logo-dark.3ScQl.png"},"shadow":{"size":0}}},"accent":{"by":"custom","hsl":{"h":211,"s":100,"l":49},"rgb":{"r":0,"g":121,"b":252}},"color":{"by":"theme","hsl":{"h":0,"s":0,"l":0},"rgb":{"r":0,"g":0,"b":0},"opacity":100},"background":{"show":false,"type":"image","opacity":100,"image":{"url":""},"video":{"url":""}},"border":0,"shape":{"wide":false,"tall":false},"timestamp":1706022248355},{"url":"https://rudub.online/","display":{"alignment":"center-center","direction":"vertical","order":"visual-name","rotate":0,"translate":{"x":0,"y":0},"gutter":25,"name":{"show":true,"text":"","size":7},"visual":{"show":true,"type":"image","size":86,"letter":{"text":""},"icon":{"name":"","prefix":"","label":""},"image":{"url":"http://rudub.site/img/rudub-logo.png"},"shadow":{"size":0}}},"accent":{"by":"custom","hsl":{"h":30,"s":91,"l":55},"rgb":{"r":245,"g":138,"b":34}},"color":{"by":"theme","hsl":{"h":0,"s":0,"l":0},"rgb":{"r":0,"g":0,"b":0},"opacity":100},"background":{"show":false,"type":"image","opacity":100,"image":{"url":""},"video":{"url":""}},"border":0,"shape":{"wide":false,"tall":false},"timestamp":1685287913984},{"url":"https://rutube.ru/","display":{"alignment":"center-center","direction":"horizontal","order":"visual-name","rotate":0,"translate":{"x":0,"y":0},"gutter":25,"name":{"show":true,"text":"RuTube","size":17},"visual":{"show":true,"type":"image","size":28,"letter":{"text":"Rutube"},"icon":{"name":"","prefix":"","label":""},"image":{"url":"https://static.rutube.ru/static/img/favicon-icons/icon_512x512.png"},"shadow":{"size":0}}},"accent":{"by":"custom","hsl":{"h":213,"s":49,"l":16},"rgb":{"r":21,"g":39,"b":61}},"color":{"by":"theme","hsl":{"h":215,"s":56,"l":16},"rgb":{"r":18,"g":37,"b":64},"opacity":100},"background":{"show":false,"type":"image","opacity":100,"image":{"url":""},"video":{"url":""}},"border":0,"shape":{"wide":false,"tall":false},"timestamp":1681064625071},{"url":"https://fanserials.vip/series/","display":{"alignment":"center-center","direction":"horizontal","order":"visual-name","rotate":0,"translate":{"x":0,"y":0},"gutter":25,"name":{"show":false,"text":"FanSerials","size":14},"visual":{"show":true,"type":"image","size":92,"letter":{"text":"FanSerials"},"icon":{"name":"","prefix":"","label":""},"image":{"url":"https://asset.brandfetch.io/idsG75Fs94/idXcTYdLn_.png"},"shadow":{"size":0}}},"accent":{"by":"custom","hsl":{"h":29,"s":81,"l":53},"rgb":{"r":232,"g":132,"b":36}},"color":{"by":"theme","hsl":{"h":28,"s":88,"l":47},"rgb":{"r":224,"g":113,"b":14},"opacity":100},"background":{"show":false,"type":"image","opacity":100,"image":{"url":""},"video":{"url":""}},"border":0,"shape":{"wide":false,"tall":false},"timestamp":1681064461495},{"url":"https://byrut.org/","display":{"alignment":"center-center","direction":"vertical","order":"visual-name","rotate":0,"translate":{"x":0,"y":0},"gutter":25,"name":{"show":true,"text":"","size":7},"visual":{"show":true,"type":"image","size":86,"letter":{"text":"byrut.org"},"icon":{"name":"","prefix":"","label":""},"image":{"url":"https://kurai.vivaldi.net/wp-content/uploads/sites/2391/2019/09/RUTOR.png"},"shadow":{"size":0}}},"accent":{"by":"custom","hsl":{"h":356,"s":100,"l":28},"rgb":{"r":142,"g":0,"b":10}},"color":{"by":"theme","hsl":{"h":0,"s":0,"l":100},"rgb":{"r":255,"g":255,"b":255},"opacity":100},"background":{"show":false,"type":"image","opacity":100,"image":{"url":""},"video":{"url":""}},"border":0,"shape":{"wide":false,"tall":false},"timestamp":1681064486649},{"url":"https://mail.yandex.ru/?uid=448276667#tabs/relevant","display":{"alignment":"center-center","direction":"vertical","order":"visual-name","rotate":0,"translate":{"x":0,"y":0},"gutter":25,"name":{"show":false,"text":"","size":7},"visual":{"show":true,"type":"image","size":76,"letter":{"text":"Я.Почта"},"icon":{"name":"","prefix":"","label":""},"image":{"url":"https://upload.wikimedia.org/wikipedia/commons/5/55/Yandex_Mail_icon.svg"},"shadow":{"size":0}}},"accent":{"by":"custom","hsl":{"h":48,"s":99,"l":62},"rgb":{"r":254,"g":214,"b":62}},"color":{"by":"theme","hsl":{"h":0,"s":20,"l":98},"rgb":{"r":251,"g":249,"b":249},"opacity":100},"background":{"show":false,"type":"image","opacity":100,"image":{"url":""},"video":{"url":""}},"border":0,"shape":{"wide":false,"tall":false},"timestamp":1681064438240},{"url":"https://aliexpress.ru/","display":{"alignment":"center-center","direction":"vertical","order":"visual-name","rotate":0,"translate":{"x":0,"y":0},"gutter":25,"name":{"show":false,"text":"AliExpress","size":7},"visual":{"show":true,"type":"image","size":121,"letter":{"text":"AliExpress"},"icon":{"name":"","prefix":"","label":"AliExpress"},"image":{"url":"https://www.logo.wine/a/logo/AliExpress/AliExpress-Logo.wine.svg"},"shadow":{"size":0}}},"accent":{"by":"custom","hsl":{"h":7,"s":80,"l":45},"rgb":{"r":207,"g":45,"b":23}},"color":{"by":"theme","hsl":{"h":11,"s":96,"l":33},"rgb":{"r":163,"g":33,"b":3},"opacity":100},"background":{"show":false,"type":"image","opacity":100,"image":{"url":""},"video":{"url":""}},"border":0,"shape":{"wide":false,"tall":false},"timestamp":1681064400020},{"url":"https://market.yandex.ru/","display":{"alignment":"center-center","direction":"horizontal","order":"visual-name","rotate":0,"translate":{"x":1,"y":3},"gutter":15,"name":{"show":false,"text":"Я.Маркет","size":14},"visual":{"show":true,"type":"image","size":60,"letter":{"text":""},"icon":{"name":"yandex","prefix":"fab","label":"Yandex"},"image":{"url":"https://yastatic.net/market-export/_/i/favicon/ymnew/194.png"},"shadow":{"size":0}}},"accent":{"by":"custom","hsl":{"h":59,"s":100,"l":51},"rgb":{"r":255,"g":251,"b":4}},"color":{"by":"theme","hsl":{"h":217,"s":100,"l":3},"rgb":{"r":0,"g":5,"b":13},"opacity":100},"background":{"show":false,"type":"image","opacity":100,"image":{"url":""},"video":{"url":""}},"border":0,"shape":{"wide":false,"tall":false},"timestamp":1681145863709},{"url":"http://192.168.0.1/","display":{"alignment":"center-center","direction":"vertical","order":"visual-name","rotate":0,"translate":{"x":0,"y":0},"gutter":25,"name":{"show":true,"text":"","size":77},"visual":{"show":true,"type":"image","size":67,"letter":{"text":""},"icon":{"name":"","prefix":"","label":""},"image":{"url":"https://cdn-images-1.medium.com/v2/resize:fit:1200/1*GJPkYmnOvsELITmuE66SyA.png"},"shadow":{"size":0}}},"accent":{"by":"custom","hsl":{"h":184,"s":62,"l":56},"rgb":{"r":74,"g":204,"b":213}},"color":{"by":"theme","hsl":{"h":0,"s":0,"l":0},"rgb":{"r":0,"g":0,"b":0},"opacity":100},"background":{"show":false,"type":"image","opacity":100,"image":{"url":""},"video":{"url":""}},"border":0,"shape":{"wide":false,"tall":false},"timestamp":1681576789532},{"url":"https://www.cdek.ru/ru/cabinet/orders","display":{"alignment":"center-center","direction":"vertical","order":"visual-name","rotate":0,"translate":{"x":0,"y":0},"gutter":25,"name":{"show":true,"text":"","size":7},"visual":{"show":true,"type":"image","size":67,"letter":{"text":"Chrome Store"},"icon":{"name":"","prefix":"","label":""},"image":{"url":"https://www.cdek.ru/storage/source/logo/1/WwRC73vQdmjyYz-FuqiKlHCMWdW2xv0P.svg"},"shadow":{"size":0}}},"accent":{"by":"custom","hsl":{"h":140,"s":100,"l":35},"rgb":{"r":0,"g":179,"b":60}},"color":{"by":"theme","hsl":{"h":207,"s":100,"l":45},"rgb":{"r":0,"g":127,"b":230},"opacity":100},"background":{"show":false,"type":"image","opacity":100,"image":{"url":""},"video":{"url":""}},"border":0,"shape":{"wide":false,"tall":false},"timestamp":1681064592730},{"url":"https://ya.ru","display":{"alignment":"center-center","direction":"horizontal","order":"visual-name","rotate":0,"translate":{"x":0,"y":0},"gutter":25,"name":{"show":false,"text":"Яндекс","size":13},"visual":{"show":true,"type":"icon","size":58,"letter":{"text":"Yandex"},"icon":{"name":"yandex-international","prefix":"fab","label":"Yandex International"},"image":{"url":""},"shadow":{"size":0}}},"accent":{"by":"custom","hsl":{"h":9,"s":100,"l":56},"rgb":{"r":255,"g":64,"b":29}},"color":{"by":"theme","hsl":{"h":9,"s":100,"l":56},"rgb":{"r":255,"g":64,"b":29},"opacity":100},"background":{"show":false,"type":"image","opacity":100,"image":{"url":""},"video":{"url":""}},"border":0,"shape":{"wide":false,"tall":false},"timestamp":1681064197882},{"url":"https://disk.yandex.ru/client/disk","display":{"alignment":"center-center","direction":"vertical","order":"visual-name","rotate":0,"translate":{"x":0,"y":0},"gutter":25,"name":{"show":true,"text":"","size":7},"visual":{"show":true,"type":"image","size":60,"letter":{"text":"Я.Диск"},"icon":{"name":"","prefix":"","label":""},"image":{"url":"https://upload.wikimedia.org/wikipedia/commons/f/f6/YandexDisk.png"},"shadow":{"size":0}}},"accent":{"by":"custom","hsl":{"h":212,"s":100,"l":50},"rgb":{"r":0,"g":119,"b":255}},"color":{"by":"theme","hsl":{"h":211,"s":97,"l":39},"rgb":{"r":3,"g":95,"b":194},"opacity":100},"background":{"show":false,"type":"image","opacity":100,"image":{"url":""},"video":{"url":""}},"border":0,"shape":{"wide":false,"tall":false},"timestamp":1681064502193},{"url":"https://hub.mos.ru/","display":{"alignment":"center-center","direction":"vertical","order":"visual-name","rotate":0,"translate":{"x":0,"y":0},"gutter":25,"name":{"show":true,"text":"","size":7},"visual":{"show":true,"type":"image","size":63,"letter":{"text":"<svg width=\"139\" height=\"29\" viewBox=\"0 0 139 29\" fill=\"none\" xmlns=\"http://www.w3.org/2000/svg\"><path d=\"M38.6742 8.06164H41.2108V10.3376C41.3599 10.0004 41.5591 9.68011 41.8078 9.37667C42.0565 9.05634 42.3384 8.77815 42.6532 8.54213C42.9848 8.3061 43.3414 8.12065 43.7226 7.98578C44.1041 7.8509 44.5101 7.78348 44.9414 7.78348C46.0354 7.78348 46.8894 8.0195 47.5029 8.49155C48.1162 8.9636 48.5392 9.57896 48.7713 10.3376C49.1527 9.57896 49.683 8.9636 50.363 8.49155C51.0592 8.0195 51.8634 7.78348 52.7754 7.78348C54.1513 7.78348 55.2125 8.19652 55.9585 9.02261C56.7049 9.84871 57.0777 11.13 57.0777 12.8665V21.4646H54.3422V13.4987C54.3422 12.3017 54.1184 11.4588 53.6706 10.9698C53.2396 10.4641 52.6509 10.2112 51.9049 10.2112C51.0094 10.2112 50.3381 10.5231 49.8905 11.1469C49.4592 11.7538 49.2437 12.5377 49.2437 13.4987V21.4646H46.5082V13.4987C46.5082 12.3017 46.2841 11.4588 45.8366 10.9698C45.4056 10.4641 44.8169 10.2112 44.0709 10.2112C43.1754 10.2112 42.5041 10.5231 42.0565 11.1469C41.6252 11.7538 41.4097 12.5377 41.4097 13.4987V21.4646H38.6742V8.06164Z\" fill=\"#CC0029\"></path><path d=\"M66.1554 21.7428C65.2433 21.7428 64.3894 21.5995 63.5935 21.3129C62.8143 21.0094 62.1346 20.5711 61.5543 19.9979C60.9739 19.4247 60.518 18.7166 60.1864 17.8736C59.855 17.0139 59.689 16.0192 59.689 14.8896V14.3838C59.689 13.3217 59.855 12.386 60.1864 11.5768C60.518 10.7507 60.9739 10.0595 61.5543 9.5031C62.1346 8.9299 62.8143 8.49999 63.5935 8.21336C64.3894 7.92676 65.2433 7.78348 66.1554 7.78348C67.0671 7.78348 67.9128 7.92676 68.692 8.21336C69.4879 8.49999 70.1758 8.9299 70.7562 9.5031C71.3366 10.0595 71.7924 10.7507 72.1241 11.5768C72.4555 12.386 72.6215 13.3217 72.6215 14.3838V14.8896C72.6215 16.0192 72.4555 17.0139 72.1241 17.8736C71.7924 18.7166 71.3366 19.4247 70.7562 19.9979C70.1758 20.5711 69.4879 21.0094 68.692 21.3129C67.9128 21.5995 67.0671 21.7428 66.1554 21.7428ZM66.1554 19.3151C66.6361 19.3151 67.092 19.2308 67.523 19.0622C67.9709 18.8936 68.3603 18.6323 68.692 18.2783C69.04 17.9242 69.3136 17.4691 69.5128 16.9127C69.7282 16.3563 69.8358 15.682 69.8358 14.8896V14.3838C69.8358 13.6589 69.7282 13.0351 69.5128 12.5125C69.3136 11.9898 69.04 11.5599 68.692 11.2227C68.3603 10.8855 67.9709 10.6327 67.523 10.4641C67.092 10.2955 66.6361 10.2112 66.1554 10.2112C65.6743 10.2112 65.2101 10.2955 64.7626 10.4641C64.3313 10.6327 63.9418 10.8855 63.5935 11.2227C63.2622 11.5599 62.9886 11.9898 62.7728 12.5125C62.5739 13.0351 62.4746 13.6589 62.4746 14.3838V14.8896C62.4746 15.682 62.5739 16.3563 62.7728 16.9127C62.9886 17.4691 63.2622 17.9242 63.5935 18.2783C63.9418 18.6323 64.3313 18.8936 64.7626 19.0622C65.2101 19.2308 65.6743 19.3151 66.1554 19.3151Z\" fill=\"#CC0029\"></path><path d=\"M80.3217 21.7428C79.3432 21.7428 78.5062 21.6332 77.8096 21.4141C77.13 21.1949 76.5579 20.8999 76.0938 20.529C75.6462 20.1581 75.2979 19.7282 75.0492 19.2393C74.8171 18.7335 74.6677 18.2109 74.6016 17.6714H77.3372C77.4534 18.1434 77.7353 18.5396 78.1828 18.8599C78.6304 19.1634 79.3432 19.3151 80.3217 19.3151C81.416 19.3151 82.187 19.1634 82.6345 18.8599C83.0821 18.5565 83.3059 18.1603 83.3059 17.6714C83.3059 17.4522 83.2481 17.2499 83.1319 17.0644C83.0157 16.8621 82.8251 16.6851 82.5598 16.5334C82.3112 16.3648 81.9712 16.213 81.5402 16.0782C81.1092 15.9433 80.5704 15.8337 79.9236 15.7494C79.1775 15.6483 78.4979 15.5049 77.8843 15.3195C77.2708 15.1172 76.7485 14.8559 76.3175 14.5356C75.8866 14.2152 75.5549 13.8275 75.3228 13.3723C75.0907 12.9171 74.9745 12.3691 74.9745 11.7285C74.9745 11.189 75.0824 10.6833 75.2979 10.2112C75.5134 9.72228 75.8451 9.3008 76.2926 8.94675C76.7402 8.5927 77.2957 8.31454 77.959 8.11221C78.6387 7.89307 79.4262 7.78348 80.3217 7.78348C81.1836 7.78348 81.93 7.89307 82.5598 8.11221C83.19 8.33139 83.7123 8.62643 84.1266 8.99733C84.5579 9.36823 84.881 9.80658 85.0965 10.3124C85.3289 10.8012 85.4779 11.3155 85.5443 11.855H82.8085C82.676 11.3323 82.4024 10.9277 81.9878 10.6411C81.59 10.3545 81.0345 10.2112 80.3217 10.2112C79.3432 10.2112 78.6636 10.3629 78.2824 10.6664C77.9009 10.9698 77.7104 11.3239 77.7104 11.7285C77.7104 11.9646 77.7601 12.1753 77.8594 12.3607C77.959 12.5462 78.1247 12.7148 78.3568 12.8665C78.5889 13.0014 78.904 13.1278 79.302 13.2458C79.7164 13.3638 80.2387 13.4566 80.8688 13.524C81.6315 13.6252 82.3278 13.7769 82.9579 13.9792C83.6044 14.1815 84.1515 14.4513 84.5991 14.7884C85.0636 15.1088 85.4198 15.5134 85.6685 16.0023C85.9172 16.4744 86.0417 17.0307 86.0417 17.6714C86.0417 18.2445 85.9172 18.784 85.6685 19.2898C85.4364 19.7787 85.0802 20.2087 84.5991 20.5796C84.1349 20.9336 83.538 21.2202 82.8085 21.4394C82.0957 21.6417 81.2666 21.7428 80.3217 21.7428Z\" fill=\"#CC0029\"></path><path d=\"M90.892 21.7428C90.3286 21.7428 89.8558 21.5489 89.4746 21.1612C89.0931 20.7734 88.9025 20.2929 88.9025 19.7197C88.9025 19.1296 89.0931 18.6491 89.4746 18.2782C89.8558 17.8905 90.3286 17.6966 90.892 17.6966C91.4558 17.6966 91.9286 17.8905 92.3097 18.2782C92.6912 18.6491 92.8818 19.1296 92.8818 19.7197C92.8818 20.2929 92.6912 20.7734 92.3097 21.1612C91.9286 21.5489 91.4558 21.7428 90.892 21.7428Z\" fill=\"#CC0029\"></path><path d=\"M96.4773 3.76256H99.2131V10.1859C99.3622 9.88243 99.5531 9.58739 99.7851 9.30079C100.017 8.99731 100.299 8.736 100.63 8.51683C100.979 8.29765 101.369 8.12064 101.8 7.98576C102.247 7.85089 102.753 7.78347 103.317 7.78347C104.925 7.78347 106.135 8.23023 106.948 9.12375C107.76 10.0004 108.166 11.2902 108.166 12.9929V21.4646H105.431V13.6251C105.431 12.4956 105.198 11.6442 104.734 11.071C104.27 10.4978 103.507 10.2112 102.446 10.2112C101.866 10.2112 101.369 10.3123 100.954 10.5146C100.556 10.7001 100.224 10.953 99.9591 11.2733C99.7105 11.5768 99.5199 11.9392 99.3871 12.3607C99.2712 12.7653 99.2131 13.1868 99.2131 13.6251V21.4646H96.4773V3.76256Z\" fill=\"#CC0029\"></path><path d=\"M116.136 21.7428C114.577 21.7428 113.4 21.2876 112.604 20.3772C111.808 19.45 111.41 18.0422 111.41 16.154V8.06161H114.146V15.9011C114.146 17.0307 114.37 17.8821 114.818 18.4552C115.282 19.0285 116.011 19.3151 117.006 19.3151C117.553 19.3151 118.018 19.2224 118.399 19.0369C118.797 18.8515 119.12 18.5986 119.369 18.2782C119.618 17.9579 119.8 17.5955 119.916 17.1908C120.048 16.7694 120.115 16.3394 120.115 15.9011V8.06161H122.85V21.4646H120.314V19.1886C119.999 19.8799 119.485 20.4783 118.772 20.9841C118.076 21.4899 117.197 21.7428 116.136 21.7428Z\" fill=\"#CC0029\"></path><path d=\"M133.339 21.7428C132.245 21.7428 131.3 21.4899 130.504 20.9841C129.725 20.4784 129.177 19.8883 128.862 19.2139V21.4646H126.326V3.76256H129.062V10.1859C129.476 9.49465 130.04 8.92145 130.753 8.46625C131.482 8.01105 132.344 7.78347 133.339 7.78347C135.047 7.78347 136.398 8.33138 137.393 9.42723C138.388 10.5231 138.885 12.1753 138.885 14.3838V14.8896C138.885 16.036 138.752 17.0391 138.487 17.8989C138.222 18.7587 137.84 19.4753 137.343 20.0485C136.862 20.6048 136.282 21.0263 135.602 21.3129C134.922 21.5995 134.168 21.7428 133.339 21.7428ZM132.692 19.3151C133.704 19.3151 134.525 18.9526 135.154 18.2277C135.785 17.5027 136.1 16.39 136.1 14.8896V14.3838C136.1 12.9676 135.793 11.9224 135.179 11.248C134.566 10.5568 133.737 10.2112 132.692 10.2112C132.212 10.2112 131.756 10.2871 131.325 10.4388C130.894 10.5905 130.504 10.8181 130.156 11.1216C129.824 11.4082 129.559 11.7791 129.36 12.2343C129.161 12.6726 129.062 13.1784 129.062 13.7516V15.5218C129.062 16.1625 129.161 16.7188 129.36 17.1909C129.559 17.6629 129.824 18.0591 130.156 18.3794C130.487 18.6997 130.869 18.9358 131.3 19.0875C131.747 19.2392 132.212 19.3151 132.692 19.3151Z\" fill=\"#CC0029\"></path><path fill-rule=\"evenodd\" clip-rule=\"evenodd\" d=\"M0 14.3181C0 8.70026 0 5.89134 1.32591 3.87356C1.89991 3.00004 2.6375 2.25003 3.49655 1.66636C5.4809 0.318115 8.24332 0.318115 13.7681 0.318115C19.2929 0.318115 22.0553 0.318115 24.0397 1.66636C24.8986 2.25003 25.6362 3.00004 26.2103 3.87356C27.5362 5.89134 27.5362 8.70026 27.5362 14.3181C27.5362 19.936 27.5362 22.7449 26.2103 24.7627C25.6362 25.6363 24.8986 26.3863 24.0397 26.9699C22.0553 28.3181 19.2929 28.3181 13.7681 28.3181C8.24332 28.3181 5.4809 28.3181 3.49655 26.9699C2.6375 26.3863 1.89991 25.6363 1.32591 24.7627C0 22.7449 0 19.936 0 14.3181ZM10.4923 26.4413C9.30924 26.4235 8.3307 26.3841 7.48998 26.2971C6.00553 26.1435 5.15503 25.8573 4.51389 25.4217C3.85477 24.9739 3.28886 24.3985 2.84846 23.7283C2.42006 23.0763 2.1385 22.2115 1.9875 20.7019C1.90186 19.846 1.86313 18.8496 1.84561 17.6447H5.97638C6.36257 19.9916 8.18425 21.8439 10.4923 22.2367V26.4413ZM12.3234 26.4549V22.2367C14.9292 21.7933 16.9151 19.4893 16.9151 16.7137C16.9151 13.6209 14.4494 11.1137 11.4079 11.1137C8.67823 11.1137 6.41241 13.133 5.97638 15.7827H1.83226C1.83123 15.3208 1.83116 14.8334 1.83116 14.3181C1.83116 12.0007 1.83262 10.2475 1.91624 8.8447L15.3416 8.84468C16.4801 8.8447 17.2419 8.84666 17.8094 8.92426C18.3506 8.99824 18.5762 9.1253 18.7234 9.27496C18.8706 9.42462 18.9955 9.65398 19.0683 10.2043C19.1446 10.7814 19.1465 11.556 19.1465 12.7137L19.1465 23.1137C19.1465 23.6279 19.5564 24.0447 20.0621 24.0447C20.5678 24.0447 20.9777 23.6279 20.9777 23.1137V12.6495C20.9777 11.5729 20.9777 10.672 20.8831 9.95618C20.7829 9.1994 20.5623 8.5116 20.0182 7.95832C19.4741 7.40504 18.7977 7.1806 18.0534 7.07886C17.3495 6.98262 16.4635 6.98266 15.4048 6.98268L2.11382 6.9827C2.27699 6.03512 2.5194 5.40878 2.84846 4.90802C3.28886 4.23782 3.85477 3.66238 4.51389 3.21456C5.15503 2.77894 6.00553 2.49264 7.48998 2.33908C9.00504 2.18237 10.9676 2.18012 13.7681 2.18012C16.5686 2.18012 18.5312 2.18237 20.0462 2.33908C21.5308 2.49264 22.3812 2.77894 23.0222 3.21456C23.6813 3.66238 24.2474 4.23782 24.6878 4.90802C25.1162 5.55998 25.3976 6.4248 25.5487 7.93426C25.7029 9.47484 25.705 11.4704 25.705 14.3181C25.705 17.1658 25.7029 19.1614 25.5487 20.7019C25.3976 22.2115 25.1162 23.0763 24.6878 23.7283C24.2474 24.3985 23.6813 24.9739 23.0222 25.4217C22.3812 25.8573 21.5308 26.1435 20.0462 26.2971C18.5312 26.4539 16.5686 26.4561 13.7681 26.4561C13.2597 26.4561 12.7789 26.4561 12.3234 26.4549ZM11.4079 20.4517C9.37761 20.4517 7.73177 18.7781 7.73177 16.7137C7.73177 14.6493 9.37761 12.9757 11.4079 12.9757C13.4381 12.9757 15.0839 14.6493 15.0839 16.7137C15.0839 18.7781 13.4381 20.4517 11.4079 20.4517Z\" fill=\"#CC0029\"></path></svg>"},"icon":{"name":"","prefix":"","label":"<svg width=\"139\" height=\"29\" viewBox=\"0 0 139 29\" fill=\"none\" xmlns=\"http://www.w3.org/2000/svg\"><path d=\"M38.6742 8.06164H41.2108V10.3376C41.3599 10.0004 41.5591 9.68011 41.8078 9.37667C42.0565 9.05634 42.3384 8.77815 42.6532 8.54213C42.9848 8.3061 43.3414 8.12065 43.7226 7.98578C44.1041 7.8509 44.5101 7.78348 44.9414 7.78348C46.0354 7.78348 46.8894 8.0195 47.5029 8.49155C48.1162 8.9636 48.5392 9.57896 48.7713 10.3376C49.1527 9.57896 49.683 8.9636 50.363 8.49155C51.0592 8.0195 51.8634 7.78348 52.7754 7.78348C54.1513 7.78348 55.2125 8.19652 55.9585 9.02261C56.7049 9.84871 57.0777 11.13 57.0777 12.8665V21.4646H54.3422V13.4987C54.3422 12.3017 54.1184 11.4588 53.6706 10.9698C53.2396 10.4641 52.6509 10.2112 51.9049 10.2112C51.0094 10.2112 50.3381 10.5231 49.8905 11.1469C49.4592 11.7538 49.2437 12.5377 49.2437 13.4987V21.4646H46.5082V13.4987C46.5082 12.3017 46.2841 11.4588 45.8366 10.9698C45.4056 10.4641 44.8169 10.2112 44.0709 10.2112C43.1754 10.2112 42.5041 10.5231 42.0565 11.1469C41.6252 11.7538 41.4097 12.5377 41.4097 13.4987V21.4646H38.6742V8.06164Z\" fill=\"#CC0029\"></path><path d=\"M66.1554 21.7428C65.2433 21.7428 64.3894 21.5995 63.5935 21.3129C62.8143 21.0094 62.1346 20.5711 61.5543 19.9979C60.9739 19.4247 60.518 18.7166 60.1864 17.8736C59.855 17.0139 59.689 16.0192 59.689 14.8896V14.3838C59.689 13.3217 59.855 12.386 60.1864 11.5768C60.518 10.7507 60.9739 10.0595 61.5543 9.5031C62.1346 8.9299 62.8143 8.49999 63.5935 8.21336C64.3894 7.92676 65.2433 7.78348 66.1554 7.78348C67.0671 7.78348 67.9128 7.92676 68.692 8.21336C69.4879 8.49999 70.1758 8.9299 70.7562 9.5031C71.3366 10.0595 71.7924 10.7507 72.1241 11.5768C72.4555 12.386 72.6215 13.3217 72.6215 14.3838V14.8896C72.6215 16.0192 72.4555 17.0139 72.1241 17.8736C71.7924 18.7166 71.3366 19.4247 70.7562 19.9979C70.1758 20.5711 69.4879 21.0094 68.692 21.3129C67.9128 21.5995 67.0671 21.7428 66.1554 21.7428ZM66.1554 19.3151C66.6361 19.3151 67.092 19.2308 67.523 19.0622C67.9709 18.8936 68.3603 18.6323 68.692 18.2783C69.04 17.9242 69.3136 17.4691 69.5128 16.9127C69.7282 16.3563 69.8358 15.682 69.8358 14.8896V14.3838C69.8358 13.6589 69.7282 13.0351 69.5128 12.5125C69.3136 11.9898 69.04 11.5599 68.692 11.2227C68.3603 10.8855 67.9709 10.6327 67.523 10.4641C67.092 10.2955 66.6361 10.2112 66.1554 10.2112C65.6743 10.2112 65.2101 10.2955 64.7626 10.4641C64.3313 10.6327 63.9418 10.8855 63.5935 11.2227C63.2622 11.5599 62.9886 11.9898 62.7728 12.5125C62.5739 13.0351 62.4746 13.6589 62.4746 14.3838V14.8896C62.4746 15.682 62.5739 16.3563 62.7728 16.9127C62.9886 17.4691 63.2622 17.9242 63.5935 18.2783C63.9418 18.6323 64.3313 18.8936 64.7626 19.0622C65.2101 19.2308 65.6743 19.3151 66.1554 19.3151Z\" fill=\"#CC0029\"></path><path d=\"M80.3217 21.7428C79.3432 21.7428 78.5062 21.6332 77.8096 21.4141C77.13 21.1949 76.5579 20.8999 76.0938 20.529C75.6462 20.1581 75.2979 19.7282 75.0492 19.2393C74.8171 18.7335 74.6677 18.2109 74.6016 17.6714H77.3372C77.4534 18.1434 77.7353 18.5396 78.1828 18.8599C78.6304 19.1634 79.3432 19.3151 80.3217 19.3151C81.416 19.3151 82.187 19.1634 82.6345 18.8599C83.0821 18.5565 83.3059 18.1603 83.3059 17.6714C83.3059 17.4522 83.2481 17.2499 83.1319 17.0644C83.0157 16.8621 82.8251 16.6851 82.5598 16.5334C82.3112 16.3648 81.9712 16.213 81.5402 16.0782C81.1092 15.9433 80.5704 15.8337 79.9236 15.7494C79.1775 15.6483 78.4979 15.5049 77.8843 15.3195C77.2708 15.1172 76.7485 14.8559 76.3175 14.5356C75.8866 14.2152 75.5549 13.8275 75.3228 13.3723C75.0907 12.9171 74.9745 12.3691 74.9745 11.7285C74.9745 11.189 75.0824 10.6833 75.2979 10.2112C75.5134 9.72228 75.8451 9.3008 76.2926 8.94675C76.7402 8.5927 77.2957 8.31454 77.959 8.11221C78.6387 7.89307 79.4262 7.78348 80.3217 7.78348C81.1836 7.78348 81.93 7.89307 82.5598 8.11221C83.19 8.33139 83.7123 8.62643 84.1266 8.99733C84.5579 9.36823 84.881 9.80658 85.0965 10.3124C85.3289 10.8012 85.4779 11.3155 85.5443 11.855H82.8085C82.676 11.3323 82.4024 10.9277 81.9878 10.6411C81.59 10.3545 81.0345 10.2112 80.3217 10.2112C79.3432 10.2112 78.6636 10.3629 78.2824 10.6664C77.9009 10.9698 77.7104 11.3239 77.7104 11.7285C77.7104 11.9646 77.7601 12.1753 77.8594 12.3607C77.959 12.5462 78.1247 12.7148 78.3568 12.8665C78.5889 13.0014 78.904 13.1278 79.302 13.2458C79.7164 13.3638 80.2387 13.4566 80.8688 13.524C81.6315 13.6252 82.3278 13.7769 82.9579 13.9792C83.6044 14.1815 84.1515 14.4513 84.5991 14.7884C85.0636 15.1088 85.4198 15.5134 85.6685 16.0023C85.9172 16.4744 86.0417 17.0307 86.0417 17.6714C86.0417 18.2445 85.9172 18.784 85.6685 19.2898C85.4364 19.7787 85.0802 20.2087 84.5991 20.5796C84.1349 20.9336 83.538 21.2202 82.8085 21.4394C82.0957 21.6417 81.2666 21.7428 80.3217 21.7428Z\" fill=\"#CC0029\"></path><path d=\"M90.892 21.7428C90.3286 21.7428 89.8558 21.5489 89.4746 21.1612C89.0931 20.7734 88.9025 20.2929 88.9025 19.7197C88.9025 19.1296 89.0931 18.6491 89.4746 18.2782C89.8558 17.8905 90.3286 17.6966 90.892 17.6966C91.4558 17.6966 91.9286 17.8905 92.3097 18.2782C92.6912 18.6491 92.8818 19.1296 92.8818 19.7197C92.8818 20.2929 92.6912 20.7734 92.3097 21.1612C91.9286 21.5489 91.4558 21.7428 90.892 21.7428Z\" fill=\"#CC0029\"></path><path d=\"M96.4773 3.76256H99.2131V10.1859C99.3622 9.88243 99.5531 9.58739 99.7851 9.30079C100.017 8.99731 100.299 8.736 100.63 8.51683C100.979 8.29765 101.369 8.12064 101.8 7.98576C102.247 7.85089 102.753 7.78347 103.317 7.78347C104.925 7.78347 106.135 8.23023 106.948 9.12375C107.76 10.0004 108.166 11.2902 108.166 12.9929V21.4646H105.431V13.6251C105.431 12.4956 105.198 11.6442 104.734 11.071C104.27 10.4978 103.507 10.2112 102.446 10.2112C101.866 10.2112 101.369 10.3123 100.954 10.5146C100.556 10.7001 100.224 10.953 99.9591 11.2733C99.7105 11.5768 99.5199 11.9392 99.3871 12.3607C99.2712 12.7653 99.2131 13.1868 99.2131 13.6251V21.4646H96.4773V3.76256Z\" fill=\"#CC0029\"></path><path d=\"M116.136 21.7428C114.577 21.7428 113.4 21.2876 112.604 20.3772C111.808 19.45 111.41 18.0422 111.41 16.154V8.06161H114.146V15.9011C114.146 17.0307 114.37 17.8821 114.818 18.4552C115.282 19.0285 116.011 19.3151 117.006 19.3151C117.553 19.3151 118.018 19.2224 118.399 19.0369C118.797 18.8515 119.12 18.5986 119.369 18.2782C119.618 17.9579 119.8 17.5955 119.916 17.1908C120.048 16.7694 120.115 16.3394 120.115 15.9011V8.06161H122.85V21.4646H120.314V19.1886C119.999 19.8799 119.485 20.4783 118.772 20.9841C118.076 21.4899 117.197 21.7428 116.136 21.7428Z\" fill=\"#CC0029\"></path><path d=\"M133.339 21.7428C132.245 21.7428 131.3 21.4899 130.504 20.9841C129.725 20.4784 129.177 19.8883 128.862 19.2139V21.4646H126.326V3.76256H129.062V10.1859C129.476 9.49465 130.04 8.92145 130.753 8.46625C131.482 8.01105 132.344 7.78347 133.339 7.78347C135.047 7.78347 136.398 8.33138 137.393 9.42723C138.388 10.5231 138.885 12.1753 138.885 14.3838V14.8896C138.885 16.036 138.752 17.0391 138.487 17.8989C138.222 18.7587 137.84 19.4753 137.343 20.0485C136.862 20.6048 136.282 21.0263 135.602 21.3129C134.922 21.5995 134.168 21.7428 133.339 21.7428ZM132.692 19.3151C133.704 19.3151 134.525 18.9526 135.154 18.2277C135.785 17.5027 136.1 16.39 136.1 14.8896V14.3838C136.1 12.9676 135.793 11.9224 135.179 11.248C134.566 10.5568 133.737 10.2112 132.692 10.2112C132.212 10.2112 131.756 10.2871 131.325 10.4388C130.894 10.5905 130.504 10.8181 130.156 11.1216C129.824 11.4082 129.559 11.7791 129.36 12.2343C129.161 12.6726 129.062 13.1784 129.062 13.7516V15.5218C129.062 16.1625 129.161 16.7188 129.36 17.1909C129.559 17.6629 129.824 18.0591 130.156 18.3794C130.487 18.6997 130.869 18.9358 131.3 19.0875C131.747 19.2392 132.212 19.3151 132.692 19.3151Z\" fill=\"#CC0029\"></path><path fill-rule=\"evenodd\" clip-rule=\"evenodd\" d=\"M0 14.3181C0 8.70026 0 5.89134 1.32591 3.87356C1.89991 3.00004 2.6375 2.25003 3.49655 1.66636C5.4809 0.318115 8.24332 0.318115 13.7681 0.318115C19.2929 0.318115 22.0553 0.318115 24.0397 1.66636C24.8986 2.25003 25.6362 3.00004 26.2103 3.87356C27.5362 5.89134 27.5362 8.70026 27.5362 14.3181C27.5362 19.936 27.5362 22.7449 26.2103 24.7627C25.6362 25.6363 24.8986 26.3863 24.0397 26.9699C22.0553 28.3181 19.2929 28.3181 13.7681 28.3181C8.24332 28.3181 5.4809 28.3181 3.49655 26.9699C2.6375 26.3863 1.89991 25.6363 1.32591 24.7627C0 22.7449 0 19.936 0 14.3181ZM10.4923 26.4413C9.30924 26.4235 8.3307 26.3841 7.48998 26.2971C6.00553 26.1435 5.15503 25.8573 4.51389 25.4217C3.85477 24.9739 3.28886 24.3985 2.84846 23.7283C2.42006 23.0763 2.1385 22.2115 1.9875 20.7019C1.90186 19.846 1.86313 18.8496 1.84561 17.6447H5.97638C6.36257 19.9916 8.18425 21.8439 10.4923 22.2367V26.4413ZM12.3234 26.4549V22.2367C14.9292 21.7933 16.9151 19.4893 16.9151 16.7137C16.9151 13.6209 14.4494 11.1137 11.4079 11.1137C8.67823 11.1137 6.41241 13.133 5.97638 15.7827H1.83226C1.83123 15.3208 1.83116 14.8334 1.83116 14.3181C1.83116 12.0007 1.83262 10.2475 1.91624 8.8447L15.3416 8.84468C16.4801 8.8447 17.2419 8.84666 17.8094 8.92426C18.3506 8.99824 18.5762 9.1253 18.7234 9.27496C18.8706 9.42462 18.9955 9.65398 19.0683 10.2043C19.1446 10.7814 19.1465 11.556 19.1465 12.7137L19.1465 23.1137C19.1465 23.6279 19.5564 24.0447 20.0621 24.0447C20.5678 24.0447 20.9777 23.6279 20.9777 23.1137V12.6495C20.9777 11.5729 20.9777 10.672 20.8831 9.95618C20.7829 9.1994 20.5623 8.5116 20.0182 7.95832C19.4741 7.40504 18.7977 7.1806 18.0534 7.07886C17.3495 6.98262 16.4635 6.98266 15.4048 6.98268L2.11382 6.9827C2.27699 6.03512 2.5194 5.40878 2.84846 4.90802C3.28886 4.23782 3.85477 3.66238 4.51389 3.21456C5.15503 2.77894 6.00553 2.49264 7.48998 2.33908C9.00504 2.18237 10.9676 2.18012 13.7681 2.18012C16.5686 2.18012 18.5312 2.18237 20.0462 2.33908C21.5308 2.49264 22.3812 2.77894 23.0222 3.21456C23.6813 3.66238 24.2474 4.23782 24.6878 4.90802C25.1162 5.55998 25.3976 6.4248 25.5487 7.93426C25.7029 9.47484 25.705 11.4704 25.705 14.3181C25.705 17.1658 25.7029 19.1614 25.5487 20.7019C25.3976 22.2115 25.1162 23.0763 24.6878 23.7283C24.2474 24.3985 23.6813 24.9739 23.0222 25.4217C22.3812 25.8573 21.5308 26.1435 20.0462 26.2971C18.5312 26.4539 16.5686 26.4561 13.7681 26.4561C13.2597 26.4561 12.7789 26.4561 12.3234 26.4549ZM11.4079 20.4517C9.37761 20.4517 7.73177 18.7781 7.73177 16.7137C7.73177 14.6493 9.37761 12.9757 11.4079 12.9757C13.4381 12.9757 15.0839 14.6493 15.0839 16.7137C15.0839 18.7781 13.4381 20.4517 11.4079 20.4517Z\" fill=\"#CC0029\"></path></svg>"},"image":{"url":"https://hub.mos.ru/mos/src/mos-icons/-/raw/sisyphus/icons-mos-classic/scalable/apps/mostechwb.svg"},"shadow":{"size":0}}},"accent":{"by":"custom","hsl":{"h":1,"s":70,"l":46},"rgb":{"r":201,"g":39,"b":35}},"color":{"by":"theme","hsl":{"h":269,"s":42,"l":44},"rgb":{"r":109,"g":64,"b":158},"opacity":100},"background":{"show":false,"type":"image","opacity":100,"image":{"url":""},"video":{"url":""}},"border":0,"shape":{"wide":false,"tall":false},"timestamp":1681064568380},{"url":"https://rutracker.org/forum/index.php","display":{"alignment":"center-center","direction":"vertical","order":"visual-name","rotate":0,"translate":{"x":0,"y":0},"gutter":25,"name":{"show":false,"text":"https://wf.cdn.gmru.net/static/wf.mail.ru/img/main/page/logo.png","size":7},"visual":{"show":true,"type":"image","size":95,"letter":{"text":""},"icon":{"name":"","prefix":"","label":""},"image":{"url":"https://upload.wikimedia.org/wikipedia/commons/thumb/d/da/Rutracker.org_logo.svg/512px-Rutracker.org_logo.svg.png?20200421015520"},"shadow":{"size":0}}},"accent":{"by":"custom","hsl":{"h":92,"s":56,"l":48},"rgb":{"r":118,"g":191,"b":54}},"color":{"by":"theme","hsl":{"h":0,"s":0,"l":0},"rgb":{"r":0,"g":0,"b":0},"opacity":100},"background":{"show":false,"type":"image","opacity":100,"image":{"url":""},"video":{"url":""}},"border":0,"shape":{"wide":false,"tall":false},"timestamp":1706109554737},{"url":"https://fumodub.ru","display":{"alignment":"center-center","direction":"vertical","order":"visual-name","rotate":0,"translate":{"x":0,"y":0},"gutter":25,"name":{"show":false,"text":"FumoDub","size":7},"visual":{"show":true,"type":"image","size":79,"letter":{"text":""},"icon":{"name":"","prefix":"","label":""},"image":{"url":"https://fumodub.ru/templates/fumodub/images/favicon.ico"},"shadow":{"size":0}}},"accent":{"by":"custom","hsl":{"h":200,"s":97,"l":86},"rgb":{"r":187,"g":232,"b":254}},"color":{"by":"theme","hsl":{"h":0,"s":0,"l":0},"rgb":{"r":0,"g":0,"b":0},"opacity":100},"background":{"show":false,"type":"image","opacity":100,"image":{"url":""},"video":{"url":""}},"border":0,"shape":{"wide":false,"tall":false},"timestamp":1710004499645},{"url":"https://track24.ru","display":{"alignment":"center-center","direction":"vertical","order":"visual-name","rotate":0,"translate":{"x":0,"y":0},"gutter":25,"name":{"show":true,"text":"","size":7},"visual":{"show":true,"type":"image","size":52,"letter":{"text":""},"icon":{"name":"","prefix":"","label":""},"image":{"url":"https://track24.ru/img/icons/48x48.png"},"shadow":{"size":0}}},"accent":{"by":"custom","hsl":{"h":206,"s":99,"l":35},"rgb":{"r":1,"g":101,"b":177}},"color":{"by":"theme","hsl":{"h":0,"s":0,"l":0},"rgb":{"r":0,"g":0,"b":0},"opacity":100},"background":{"show":false,"type":"image","opacity":100,"image":{"url":""},"video":{"url":""}},"border":0,"shape":{"wide":false,"tall":false},"timestamp":1706342274022},{"url":"https://www.ozon.ru/","display":{"alignment":"center-center","direction":"vertical","order":"visual-name","rotate":0,"translate":{"x":0,"y":0},"gutter":25,"name":{"show":true,"text":"","size":7},"visual":{"show":true,"type":"image","size":125,"letter":{"text":"Ozon"},"icon":{"name":"","prefix":"","label":""},"image":{"url":"https://docs.ozon.ru/company/images/logo_Ozon_new.png"},"shadow":{"size":0}}},"accent":{"by":"custom","hsl":{"h":219,"s":100,"l":50},"rgb":{"r":0,"g":89,"b":255}},"color":{"by":"theme","hsl":{"h":233,"s":100,"l":50},"rgb":{"r":0,"g":31,"b":255},"opacity":100},"background":{"show":false,"type":"image","opacity":100,"image":{"url":""},"video":{"url":""}},"border":0,"shape":{"wide":false,"tall":false},"timestamp":1681064529042},{"url":"https://bigenc.ru/","display":{"alignment":"center-center","direction":"vertical","order":"visual-name","rotate":0,"translate":{"x":0,"y":0},"gutter":25,"name":{"show":true,"text":"","size":7},"visual":{"show":true,"type":"image","size":95,"letter":{"text":""},"icon":{"name":"","prefix":"","label":""},"image":{"url":"https://bigenc.ru/_nuxt/logo.73f149c4.svg"},"shadow":{"size":0}}},"accent":{"by":"theme","hsl":{"h":0,"s":0,"l":0},"rgb":{"r":0,"g":0,"b":0}},"color":{"by":"theme","hsl":{"h":0,"s":0,"l":0},"rgb":{"r":0,"g":0,"b":0},"opacity":100},"background":{"show":false,"type":"image","opacity":100,"image":{"url":""},"video":{"url":""}},"border":0,"shape":{"wide":false,"tall":false},"timestamp":1689967365696}]}]}